{
    "level": {
        "timeToPlay": 360,
        "numberCellLock": 4,
        "itemHiden": 6,
        "cells": [
            {
                "posX": -10,
                "posY": 4,
                "cellType": 0,
                "numberLayer": 0,
                "moveType": 0,
                "speed": 0,
                "isLock": 1,
                "itemsLayer": [
                    {
                        "items": [
                            29,
                            292,
                            292
                        ]
                    },
                    {
                        "items": [
                            0,
                            196,
                            196
                        ]
                    },
                    {
                        "items": [
                            48,
                            161,
                            72
                        ]
                    },
                    {
                        "items": [
                            306,
                            243,
                            306
                        ]
                    },
                    {
                        "items": [
                            176,
                            0,
                            176
                        ]
                    },
                    {
                        "items": [
                            0,
                            53,
                            0
                        ]
                    }
                ]
            },
            {
                "posX": -10,
                "posY": -4,
                "cellType": 0,
                "numberLayer": 0,
                "moveType": 0,
                "speed": 0,
                "isLock": 1,
                "itemsLayer": [
                    {
                        "items": [
                            12,
                            12,
                            313
                        ]
                    },
                    {
                        "items": [
                            331,
                            331,
                            326
                        ]
                    },
                    {
                        "items": [
                            313,
                            313,
                            310
                        ]
                    },
                    {
                        "items": [
                            113,
                            196,
                            113
                        ]
                    },
                    {
                        "items": [
                            0,
                            239,
                            122
                        ]
                    },
                    {
                        "items": [
                            0,
                            375,
                            375
                        ]
                    }
                ]
            },
            {
                "posX": -3,
                "posY": -12,
                "cellType": 0,
                "numberLayer": 0,
                "moveType": 0,
                "speed": 0,
                "isLock": 0,
                "itemsLayer": [
                    {
                        "items": [
                            36,
                            287,
                            36
                        ]
                    },
                    {
                        "items": [
                            301,
                            0,
                            301
                        ]
                    },
                    {
                        "items": [
                            0,
                            368,
                            368
                        ]
                    },
                    {
                        "items": [
                            243,
                            250,
                            250
                        ]
                    },
                    {
                        "items": [
                            127,
                            265,
                            127
                        ]
                    }
                ]
            },
            {
                "posX": -3,
                "posY": 0,
                "cellType": 0,
                "numberLayer": 0,
                "moveType": 0,
                "speed": 0,
                "isLock": 0,
                "itemsLayer": [
                    {
                        "items": [
                            0,
                            161,
                            161
                        ]
                    },
                    {
                        "items": [
                            148,
                            258,
                            148
                        ]
                    },
                    {
                        "items": [
                            380,
                            380,
                            0
                        ]
                    },
                    {
                        "items": [
                            360,
                            417,
                            360
                        ]
                    },
                    {
                        "items": [
                            0,
                            335,
                            335
                        ]
                    },
                    {
                        "items": [
                            411,
                            417,
                            417
                        ]
                    }
                ]
            },
            {
                "posX": -3,
                "posY": 4,
                "cellType": 0,
                "numberLayer": 0,
                "moveType": 0,
                "speed": 0,
                "isLock": 0,
                "itemsLayer": [
                    {
                        "items": [
                            26,
                            309,
                            368
                        ]
                    },
                    {
                        "items": [
                            337,
                            337,
                            322
                        ]
                    },
                    {
                        "items": [
                            287,
                            380,
                            301
                        ]
                    },
                    {
                        "items": [
                            259,
                            48,
                            48
                        ]
                    },
                    {
                        "items": [
                            265,
                            53,
                            265
                        ]
                    }
                ]
            },
            {
                "posX": 4,
                "posY": 4,
                "cellType": 0,
                "numberLayer": 0,
                "moveType": 0,
                "speed": 0,
                "isLock": 0,
                "itemsLayer": [
                    {
                        "items": [
                            26,
                            0,
                            26
                        ]
                    },
                    {
                        "items": [
                            147,
                            303,
                            147
                        ]
                    },
                    {
                        "items": [
                            243,
                            234,
                            75
                        ]
                    },
                    {
                        "items": [
                            51,
                            0,
                            51
                        ]
                    },
                    {
                        "items": [
                            206,
                            0,
                            206
                        ]
                    },
                    {
                        "items": [
                            0,
                            0,
                            239
                        ]
                    }
                ]
            },
            {
                "posX": -3,
                "posY": -8,
                "cellType": 0,
                "numberLayer": 0,
                "moveType": 0,
                "speed": 0,
                "isLock": 0,
                "itemsLayer": [
                    {
                        "items": [
                            288,
                            288,
                            8
                        ]
                    },
                    {
                        "items": [
                            159,
                            159,
                            0
                        ]
                    },
                    {
                        "items": [
                            300,
                            176,
                            300
                        ]
                    },
                    {
                        "items": [
                            365,
                            197,
                            365
                        ]
                    },
                    {
                        "items": [
                            53,
                            122,
                            112
                        ]
                    }
                ]
            },
            {
                "posX": -3,
                "posY": 8,
                "cellType": 0,
                "numberLayer": 0,
                "moveType": 0,
                "speed": 0,
                "isLock": 0,
                "itemsLayer": [
                    {
                        "items": [
                            29,
                            8,
                            8
                        ]
                    },
                    {
                        "items": [
                            322,
                            145,
                            145
                        ]
                    },
                    {
                        "items": [
                            145,
                            0,
                            250
                        ]
                    },
                    {
                        "items": [
                            112,
                            0,
                            112
                        ]
                    },
                    {
                        "items": [
                            126,
                            126,
                            0
                        ]
                    }
                ]
            },
            {
                "posX": -10,
                "posY": -8,
                "cellType": 0,
                "numberLayer": 0,
                "moveType": 0,
                "speed": 0,
                "isLock": 1,
                "itemsLayer": [
                    {
                        "items": [
                            306,
                            29,
                            0
                        ]
                    },
                    {
                        "items": [
                            331,
                            0,
                            326
                        ]
                    },
                    {
                        "items": [
                            310,
                            310,
                            234
                        ]
                    },
                    {
                        "items": [
                            220,
                            0,
                            260
                        ]
                    },
                    {
                        "items": [
                            329,
                            0,
                            220
                        ]
                    }
                ]
            },
            {
                "posX": 4,
                "posY": -8,
                "cellType": 0,
                "numberLayer": 0,
                "moveType": 0,
                "speed": 0,
                "isLock": 0,
                "itemsLayer": [
                    {
                        "items": [
                            159,
                            0,
                            5
                        ]
                    },
                    {
                        "items": [
                            141,
                            322,
                            141
                        ]
                    },
                    {
                        "items": [
                            0,
                            236,
                            236
                        ]
                    },
                    {
                        "items": [
                            75,
                            227,
                            75
                        ]
                    },
                    {
                        "items": [
                            0,
                            411,
                            239
                        ]
                    }
                ]
            },
            {
                "posX": -3,
                "posY": -4,
                "cellType": 0,
                "numberLayer": 0,
                "moveType": 0,
                "speed": 0,
                "isLock": 0,
                "itemsLayer": [
                    {
                        "items": [
                            5,
                            16,
                            0
                        ]
                    },
                    {
                        "items": [
                            309,
                            384,
                            309
                        ]
                    },
                    {
                        "items": [
                            12,
                            227,
                            227
                        ]
                    },
                    {
                        "items": [
                            360,
                            365,
                            113
                        ]
                    },
                    {
                        "items": [
                            220,
                            127,
                            335
                        ]
                    },
                    {
                        "items": [
                            0,
                            259,
                            0
                        ]
                    }
                ]
            },
            {
                "posX": 4,
                "posY": -4,
                "cellType": 0,
                "numberLayer": 0,
                "moveType": 0,
                "speed": 0,
                "isLock": 0,
                "itemsLayer": [
                    {
                        "items": [
                            0,
                            16,
                            16
                        ]
                    },
                    {
                        "items": [
                            337,
                            141,
                            206
                        ]
                    },
                    {
                        "items": [
                            65,
                            384,
                            384
                        ]
                    },
                    {
                        "items": [
                            65,
                            259,
                            65
                        ]
                    },
                    {
                        "items": [
                            260,
                            260,
                            0
                        ]
                    },
                    {
                        "items": [
                            0,
                            51,
                            0
                        ]
                    }
                ]
            },
            {
                "posX": 4,
                "posY": 0,
                "cellType": 0,
                "numberLayer": 0,
                "moveType": 0,
                "speed": 0,
                "isLock": 0,
                "itemsLayer": [
                    {
                        "items": [
                            36,
                            287,
                            5
                        ]
                    },
                    {
                        "items": [
                            258,
                            258,
                            0
                        ]
                    },
                    {
                        "items": [
                            312,
                            312,
                            288
                        ]
                    },
                    {
                        "items": [
                            197,
                            300,
                            197
                        ]
                    },
                    {
                        "items": [
                            375,
                            126,
                            147
                        ]
                    },
                    {
                        "items": [
                            122,
                            0,
                            0
                        ]
                    }
                ]
            },
            {
                "posX": -10,
                "posY": 0,
                "cellType": 0,
                "numberLayer": 0,
                "moveType": 0,
                "speed": 0,
                "isLock": 1,
                "itemsLayer": [
                    {
                        "items": [
                            303,
                            148,
                            303
                        ]
                    },
                    {
                        "items": [
                            0,
                            292,
                            326
                        ]
                    },
                    {
                        "items": [
                            72,
                            312,
                            72
                        ]
                    },
                    {
                        "items": [
                            115,
                            234,
                            115
                        ]
                    },
                    {
                        "items": [
                            329,
                            329,
                            236
                        ]
                    },
                    {
                        "items": [
                            0,
                            411,
                            115
                        ]
                    }
                ]
            }
        ]
    }
}