{
    "level": {
        "timeToPlay": 340,
        "numberCellLock": 4,
        "itemHiden": 6,
        "cells": [
            {
                "posX": -3,
                "posY": 0,
                "cellType": 0,
                "numberLayer": 0,
                "moveType": 0,
                "speed": 0,
                "isLock": 0,
                "itemsLayer": [
                    {
                        "items": [
                            249,
                            273,
                            286
                        ]
                    },
                    {
                        "items": [
                            277,
                            249,
                            0
                        ]
                    },
                    {
                        "items": [
                            21,
                            237,
                            236
                        ]
                    },
                    {
                        "items": [
                            216,
                            185,
                            0
                        ]
                    },
                    {
                        "items": [
                            166,
                            169,
                            221
                        ]
                    },
                    {
                        "items": [
                            143,
                            99,
                            256
                        ]
                    },
                    {
                        "items": [
                            43,
                            41,
                            41
                        ]
                    },
                    {
                        "items": [
                            0,
                            0,
                            4
                        ]
                    }
                ]
            },
            {
                "posX": -3,
                "posY": -4,
                "cellType": 0,
                "numberLayer": 0,
                "moveType": 0,
                "speed": 0,
                "isLock": 1,
                "itemsLayer": [
                    {
                        "items": [
                            0,
                            267,
                            298
                        ]
                    },
                    {
                        "items": [
                            266,
                            0,
                            267
                        ]
                    },
                    {
                        "items": [
                            240,
                            0,
                            240
                        ]
                    },
                    {
                        "items": [
                            0,
                            185,
                            231
                        ]
                    },
                    {
                        "items": [
                            223,
                            219,
                            223
                        ]
                    },
                    {
                        "items": [
                            220,
                            85,
                            220
                        ]
                    },
                    {
                        "items": [
                            51,
                            26,
                            51
                        ]
                    }
                ]
            },
            {
                "posX": -9,
                "posY": 4,
                "cellType": 0,
                "numberLayer": 0,
                "moveType": 0,
                "speed": 0,
                "isLock": 0,
                "itemsLayer": [
                    {
                        "items": [
                            0,
                            290,
                            286
                        ]
                    },
                    {
                        "items": [
                            259,
                            259,
                            0
                        ]
                    },
                    {
                        "items": [
                            255,
                            255,
                            0
                        ]
                    },
                    {
                        "items": [
                            0,
                            223,
                            217
                        ]
                    },
                    {
                        "items": [
                            0,
                            102,
                            100
                        ]
                    },
                    {
                        "items": [
                            0,
                            139,
                            139
                        ]
                    },
                    {
                        "items": [
                            27,
                            3,
                            3
                        ]
                    }
                ]
            },
            {
                "posX": 3,
                "posY": -4,
                "cellType": 0,
                "numberLayer": 0,
                "moveType": 0,
                "speed": 0,
                "isLock": 0,
                "itemsLayer": [
                    {
                        "items": [
                            278,
                            297,
                            278
                        ]
                    },
                    {
                        "items": [
                            251,
                            251,
                            239
                        ]
                    },
                    {
                        "items": [
                            239,
                            239,
                            0
                        ]
                    },
                    {
                        "items": [
                            231,
                            229,
                            216
                        ]
                    },
                    {
                        "items": [
                            224,
                            142,
                            142
                        ]
                    },
                    {
                        "items": [
                            0,
                            85,
                            22
                        ]
                    },
                    {
                        "items": [
                            48,
                            52,
                            0
                        ]
                    },
                    {
                        "items": [
                            0,
                            27,
                            43
                        ]
                    }
                ]
            },
            {
                "posX": 3,
                "posY": -8,
                "cellType": 0,
                "numberLayer": 0,
                "moveType": 0,
                "speed": 0,
                "isLock": 1,
                "itemsLayer": [
                    {
                        "items": [
                            277,
                            266,
                            267
                        ]
                    },
                    {
                        "items": [
                            300,
                            80,
                            300
                        ]
                    },
                    {
                        "items": [
                            0,
                            127,
                            127
                        ]
                    },
                    {
                        "items": [
                            217,
                            0,
                            216
                        ]
                    },
                    {
                        "items": [
                            102,
                            102,
                            0
                        ]
                    },
                    {
                        "items": [
                            0,
                            22,
                            85
                        ]
                    },
                    {
                        "items": [
                            0,
                            112,
                            48
                        ]
                    },
                    {
                        "items": [
                            0,
                            4,
                            0
                        ]
                    }
                ]
            },
            {
                "posX": -9,
                "posY": 0,
                "cellType": 0,
                "numberLayer": 0,
                "moveType": 0,
                "speed": 0,
                "isLock": 0,
                "itemsLayer": [
                    {
                        "items": [
                            19,
                            270,
                            286
                        ]
                    },
                    {
                        "items": [
                            293,
                            0,
                            293
                        ]
                    },
                    {
                        "items": [
                            240,
                            127,
                            0
                        ]
                    },
                    {
                        "items": [
                            217,
                            224,
                            233
                        ]
                    },
                    {
                        "items": [
                            221,
                            100,
                            0
                        ]
                    },
                    {
                        "items": [
                            20,
                            220,
                            20
                        ]
                    },
                    {
                        "items": [
                            0,
                            26,
                            51
                        ]
                    }
                ]
            },
            {
                "posX": 3,
                "posY": 4,
                "cellType": 0,
                "numberLayer": 0,
                "moveType": 0,
                "speed": 0,
                "isLock": 0,
                "itemsLayer": [
                    {
                        "items": [
                            273,
                            273,
                            19
                        ]
                    },
                    {
                        "items": [
                            19,
                            246,
                            249
                        ]
                    },
                    {
                        "items": [
                            236,
                            253,
                            236
                        ]
                    },
                    {
                        "items": [
                            233,
                            0,
                            233
                        ]
                    },
                    {
                        "items": [
                            0,
                            166,
                            166
                        ]
                    },
                    {
                        "items": [
                            219,
                            218,
                            3
                        ]
                    },
                    {
                        "items": [
                            103,
                            0,
                            104
                        ]
                    },
                    {
                        "items": [
                            0,
                            41,
                            43
                        ]
                    }
                ]
            },
            {
                "posX": -9,
                "posY": -8,
                "cellType": 0,
                "numberLayer": 0,
                "moveType": 0,
                "speed": 0,
                "isLock": 1,
                "itemsLayer": [
                    {
                        "items": [
                            266,
                            300,
                            277
                        ]
                    },
                    {
                        "items": [
                            0,
                            292,
                            293
                        ]
                    },
                    {
                        "items": [
                            73,
                            80,
                            73
                        ]
                    },
                    {
                        "items": [
                            229,
                            221,
                            229
                        ]
                    },
                    {
                        "items": [
                            219,
                            218,
                            218
                        ]
                    },
                    {
                        "items": [
                            22,
                            143,
                            138
                        ]
                    },
                    {
                        "items": [
                            0,
                            103,
                            48
                        ]
                    }
                ]
            },
            {
                "posX": -3,
                "posY": 8,
                "cellType": 0,
                "numberLayer": 0,
                "moveType": 0,
                "speed": 0,
                "isLock": 0,
                "itemsLayer": [
                    {
                        "items": [
                            0,
                            297,
                            297
                        ]
                    },
                    {
                        "items": [
                            246,
                            255,
                            246
                        ]
                    },
                    {
                        "items": [
                            258,
                            80,
                            258
                        ]
                    },
                    {
                        "items": [
                            232,
                            232,
                            23
                        ]
                    },
                    {
                        "items": [
                            187,
                            169,
                            224
                        ]
                    },
                    {
                        "items": [
                            158,
                            20,
                            156
                        ]
                    },
                    {
                        "items": [
                            0,
                            99,
                            99
                        ]
                    },
                    {
                        "items": [
                            104,
                            0,
                            104
                        ]
                    }
                ]
            },
            {
                "posX": -3,
                "posY": -12,
                "cellType": 0,
                "numberLayer": 0,
                "moveType": 0,
                "speed": 0,
                "isLock": 0,
                "itemsLayer": [
                    {
                        "items": [
                            270,
                            270,
                            278
                        ]
                    },
                    {
                        "items": [
                            253,
                            253,
                            251
                        ]
                    },
                    {
                        "items": [
                            73,
                            232,
                            128
                        ]
                    },
                    {
                        "items": [
                            23,
                            169,
                            0
                        ]
                    },
                    {
                        "items": [
                            0,
                            158,
                            156
                        ]
                    },
                    {
                        "items": [
                            0,
                            138,
                            256
                        ]
                    },
                    {
                        "items": [
                            112,
                            112,
                            0
                        ]
                    }
                ]
            },
            {
                "posX": -9,
                "posY": 8,
                "cellType": 0,
                "numberLayer": 0,
                "moveType": 0,
                "speed": 0,
                "isLock": 0,
                "itemsLayer": [
                    {
                        "items": [
                            290,
                            0,
                            290
                        ]
                    },
                    {
                        "items": [
                            21,
                            258,
                            259
                        ]
                    },
                    {
                        "items": [
                            0,
                            237,
                            237
                        ]
                    },
                    {
                        "items": [
                            23,
                            128,
                            231
                        ]
                    },
                    {
                        "items": [
                            100,
                            158,
                            0
                        ]
                    },
                    {
                        "items": [
                            156,
                            0,
                            138
                        ]
                    },
                    {
                        "items": [
                            103,
                            26,
                            4
                        ]
                    },
                    {
                        "items": [
                            0,
                            0,
                            27
                        ]
                    }
                ]
            },
            {
                "posX": 3,
                "posY": -12,
                "cellType": 0,
                "numberLayer": 0,
                "moveType": 0,
                "speed": 0,
                "isLock": 1,
                "itemsLayer": [
                    {
                        "items": [
                            298,
                            0,
                            298
                        ]
                    },
                    {
                        "items": [
                            0,
                            292,
                            292
                        ]
                    },
                    {
                        "items": [
                            21,
                            0,
                            128
                        ]
                    },
                    {
                        "items": [
                            187,
                            185,
                            187
                        ]
                    },
                    {
                        "items": [
                            0,
                            142,
                            139
                        ]
                    },
                    {
                        "items": [
                            0,
                            143,
                            256
                        ]
                    },
                    {
                        "items": [
                            52,
                            0,
                            52
                        ]
                    }
                ]
            }
        ]
    }
}